[
  {
    "name": "Notary",
    "homepage_url": "https://github.com/theupdateframework/notary",
    "repo_url": "https://github.com/theupdateframework/notary",
    "logo": "https://raw.githubusercontent.com/cncf/artwork/master/notary/stacked/color/notary-stacked-color.svg",
    "crunchbase": "https://www.crunchbase.com/organization/cloud-native-computing-foundation",
    "github_data": {
      "stars": 1280,
      "license": "Apache-2.0",
      "description": "Notary is a project that allows anyone to have trust over arbitrary collections of data",
      "latest_commit_date": "2018-04-07T00:00:00.000Z",
      "latest_commit_link": "/theupdateframework/notary/commit/c30d5e375318b429af87b4885c49c6dcc266f5e4",
      "release_date": "2017-08-28T22:31:30Z",
      "release_link": "https://github.com/theupdateframework/notary/releases",
      "contributors_count": 59,
      "contributors_link": "https://github.com/theupdateframework/notary/graphs/contributors"
    },
    "github_start_commit_data": {
      "start_commit_link": "/theupdateframework/notary/commit/495dce997d6353738e1f115b0d2b24fc880c959e",
      "start_date": "2015-03-27T22:57:48Z"
    },
    "cncf_membership_data": {
      "cncf_member": "cncf"
    },
    "image_data": {
      "fileName": "notary.svg"
    },
    "cncfProject": "incubating",
    "cncfMember": "cncf",
    "cncfRelation": "incubating",
    "firstCommitDate": "2015-03-27T22:57:48Z",
    "firstCommitLink": "https://github.com/theupdateframework/notary/commit/495dce997d6353738e1f115b0d2b24fc880c959e",
    "latestCommitDate": {
      "text": "this week",
      "value": "990",
      "original": "2018-04-07T00:00:00.000Z"
    },
    "latestCommitLink": "https://github.com/theupdateframework/notary/commit/c30d5e375318b429af87b4885c49c6dcc266f5e4",
    "releaseDate": {
      "text": "7 months ago",
      "value": "900",
      "original": "2017-08-28T22:31:30Z"
    },
    "releaseLink": "https://github.com/theupdateframework/notary/releases",
    "contributorsCount": 59,
    "contributorsLink": "https://github.com/theupdateframework/notary/graphs/contributors",
    "stars": 1280,
    "license": "Apache-2.0",
    "headquarters": "San Francisco, California",
    "twitter": "https://twitter.com/cloudnativefdn",
    "latestTweetDate": {
      "text": "this week",
      "value": "990",
      "original": "2018-04-08T12:57:01.000Z"
    },
    "description": "Notary is a project that allows anyone to have trust over arbitrary collections of data",
    "organization": "Cloud Native Computing Foundation (CNCF)",
    "crunchbaseData": {
      "name": "Cloud Native Computing Foundation (CNCF)",
      "description": "CNCF is an open source software foundation that hosts and nurtures projects like Kubernetes and Prometheus.",
      "homepage": "https://www.cncf.io/",
      "city": "San Francisco",
      "region": "California",
      "country": "United States",
      "twitter": "https://twitter.com/cloudnativefdn",
      "linkedin": "https://www.linkedin.com/company/cloud-native-computing-foundation",
      "numEmployeesMin": 11,
      "numEmployeesMax": 50
    },
    "path": "Provisioning / Secure Images",
    "landscape": "Provisioning / Secure Images",
    "category": "Provisioning",
    "oss": true,
    "href": "/logos/notary.svg",
    "id": "notary"
  },
  {
    "name": "The Update Framework (TUF)",
    "homepage_url": "https://theupdateframework.github.io/",
    "repo_url": "https://github.com/theupdateframework/tuf",
    "branch": "develop",
    "logo": "https://github.com/cncf/artwork/blob/master/tuf/stacked/color/tuf-stacked-color.svg",
    "crunchbase": "https://www.crunchbase.com/organization/cloud-native-computing-foundation",
    "github_data": {
      "stars": 719,
      "license": "Unknown License",
      "description": "A framework for securing software update systems",
      "latest_commit_date": "2018-04-06T00:00:00.000Z",
      "latest_commit_link": "/theupdateframework/tuf/commit/ee2300e23087aa510ca9ccca1e7db890fc23e6a0",
      "contributors_count": 34,
      "contributors_link": "https://github.com/theupdateframework/tuf/graphs/contributors"
    },
    "github_start_commit_data": {
      "start_commit_link": "/theupdateframework/tuf/commit/0fb43a5e36f40ae7fccd2128e5e0bbb401b3111a",
      "start_date": "2013-01-31T18:54:15Z"
    },
    "cncf_membership_data": {
      "cncf_member": "cncf"
    },
    "image_data": {
      "fileName": "the-update-framework-tuf.svg"
    },
    "cncfProject": "incubating",
    "cncfMember": "cncf",
    "cncfRelation": "incubating",
    "firstCommitDate": "2013-01-31T18:54:15Z",
    "firstCommitLink": "https://github.com/theupdateframework/tuf/commit/0fb43a5e36f40ae7fccd2128e5e0bbb401b3111a",
    "latestCommitDate": {
      "text": "this week",
      "value": "990",
      "original": "2018-04-06T00:00:00.000Z"
    },
    "latestCommitLink": "https://github.com/theupdateframework/tuf/commit/ee2300e23087aa510ca9ccca1e7db890fc23e6a0",
    "contributorsCount": 34,
    "contributorsLink": "https://github.com/theupdateframework/tuf/graphs/contributors",
    "stars": 719,
    "license": "Unknown License",
    "headquarters": "San Francisco, California",
    "twitter": "https://twitter.com/cloudnativefdn",
    "latestTweetDate": {
      "text": "this week",
      "value": "990",
      "original": "2018-04-08T12:57:01.000Z"
    },
    "description": "A framework for securing software update systems",
    "organization": "Cloud Native Computing Foundation (CNCF)",
    "crunchbaseData": {
      "name": "Cloud Native Computing Foundation (CNCF)",
      "description": "CNCF is an open source software foundation that hosts and nurtures projects like Kubernetes and Prometheus.",
      "homepage": "https://www.cncf.io/",
      "city": "San Francisco",
      "region": "California",
      "country": "United States",
      "twitter": "https://twitter.com/cloudnativefdn",
      "linkedin": "https://www.linkedin.com/company/cloud-native-computing-foundation",
      "numEmployeesMin": 11,
      "numEmployeesMax": 50
    },
    "path": "Provisioning / Secure Images",
    "landscape": "Provisioning / Secure Images",
    "category": "Provisioning",
    "oss": true,
    "href": "/logos/the-update-framework-tuf.svg",
    "id": "the-update-framework-tuf"
  },
  {
    "name": "SPIFFE",
    "homepage_url": "https://spiffe.io/",
    "repo_url": "https://github.com/spiffe/spiffe",
    "logo": "https://raw.githubusercontent.com/cncf/artwork/master/spiffe/stacked/color/spiffe-stacked-color.svg",
    "twitter": "https://twitter.com/spiffeio",
    "crunchbase": "https://www.crunchbase.com/organization/cloud-native-computing-foundation",
    "github_data": {
      "stars": 201,
      "license": "Apache-2.0",
      "description": "The SPIFFE Project",
      "latest_commit_date": "2018-03-30T00:00:00.000Z",
      "latest_commit_link": "/spiffe/spiffe/commit/da2d55dea4a0aef24b705667335e630cd28f8f7a",
      "contributors_count": 18,
      "contributors_link": "https://github.com/spiffe/spiffe/graphs/contributors"
    },
    "github_start_commit_data": {
      "start_commit_link": "/spiffe/spiffe/commit/f6c7cd6e6a21cf8c763f462ddd9fdb501b9b7c70",
      "start_date": "2017-01-31T06:47:40Z"
    },
    "cncf_membership_data": {
      "cncf_member": "cncf"
    },
    "image_data": {
      "fileName": "spiffe.svg"
    },
    "cncfProject": "sandbox",
    "cncfMember": "cncf",
    "cncfRelation": "sandbox",
    "firstCommitDate": "2017-01-31T06:47:40Z",
    "firstCommitLink": "https://github.com/spiffe/spiffe/commit/f6c7cd6e6a21cf8c763f462ddd9fdb501b9b7c70",
    "latestCommitDate": {
      "text": "last week",
      "value": "980",
      "original": "2018-03-30T00:00:00.000Z"
    },
    "latestCommitLink": "https://github.com/spiffe/spiffe/commit/da2d55dea4a0aef24b705667335e630cd28f8f7a",
    "contributorsCount": 18,
    "contributorsLink": "https://github.com/spiffe/spiffe/graphs/contributors",
    "stars": 201,
    "license": "Apache-2.0",
    "headquarters": "San Francisco, California",
    "latestTweetDate": {
      "text": "last week",
      "value": "980",
      "original": "2018-03-29T15:35:09.000Z"
    },
    "description": "The SPIFFE Project",
    "organization": "Cloud Native Computing Foundation (CNCF)",
    "crunchbaseData": {
      "name": "Cloud Native Computing Foundation (CNCF)",
      "description": "CNCF is an open source software foundation that hosts and nurtures projects like Kubernetes and Prometheus.",
      "homepage": "https://www.cncf.io/",
      "city": "San Francisco",
      "region": "California",
      "country": "United States",
      "twitter": "https://twitter.com/cloudnativefdn",
      "linkedin": "https://www.linkedin.com/company/cloud-native-computing-foundation",
      "numEmployeesMin": 11,
      "numEmployeesMax": 50
    },
    "path": "Provisioning / Key Management",
    "landscape": "Provisioning / Key Management",
    "category": "Provisioning",
    "oss": true,
    "href": "/logos/spiffe.svg",
    "id": "spiffe"
  },
  {
    "name": "Spire",
    "homepage_url": "https://spiffe.io/spire/",
    "repo_url": "https://github.com/spiffe/spire",
    "logo": "./hosted_logos/spire.svg",
    "twitter": "https://twitter.com/spiffeio",
    "crunchbase": "https://www.crunchbase.com/organization/cloud-native-computing-foundation",
    "github_data": {
      "stars": 159,
      "license": "Apache-2.0",
      "description": "The SPIFFE Runtime Environment",
      "latest_commit_date": "2018-04-06T00:00:00.000Z",
      "latest_commit_link": "/spiffe/spire/commit/4f3783598458d5b6bf751b6f0ff42fb1a7db143b",
      "release_date": "2017-09-26T20:02:39Z",
      "release_link": "https://github.com/spiffe/spire/releases",
      "contributors_count": 15,
      "contributors_link": "https://github.com/spiffe/spire/graphs/contributors"
    },
    "github_start_commit_data": {
      "start_commit_link": "/spiffe/spire/commit/3c42eb7b3695df5136dd44d467854fd3f119f509",
      "start_date": "2017-03-23T07:01:54Z"
    },
    "cncf_membership_data": {
      "cncf_member": "cncf"
    },
    "image_data": {
      "fileName": "spire.svg",
      "hash": "jIcHrVM1S8YvStTB7/Fumv4CJrdMeKL+HVBqrUI26j8="
    },
    "cncfProject": "sandbox",
    "cncfMember": "cncf",
    "cncfRelation": "sandbox",
    "firstCommitDate": "2017-03-23T07:01:54Z",
    "firstCommitLink": "https://github.com/spiffe/spire/commit/3c42eb7b3695df5136dd44d467854fd3f119f509",
    "latestCommitDate": {
      "text": "this week",
      "value": "990",
      "original": "2018-04-06T00:00:00.000Z"
    },
    "latestCommitLink": "https://github.com/spiffe/spire/commit/4f3783598458d5b6bf751b6f0ff42fb1a7db143b",
    "releaseDate": {
      "text": "6 months ago",
      "value": "910",
      "original": "2017-09-26T20:02:39Z"
    },
    "releaseLink": "https://github.com/spiffe/spire/releases",
    "contributorsCount": 15,
    "contributorsLink": "https://github.com/spiffe/spire/graphs/contributors",
    "stars": 159,
    "license": "Apache-2.0",
    "headquarters": "San Francisco, California",
    "latestTweetDate": {
      "text": "last week",
      "value": "980",
      "original": "2018-03-29T15:35:09.000Z"
    },
    "description": "The SPIFFE Runtime Environment",
    "organization": "Cloud Native Computing Foundation (CNCF)",
    "crunchbaseData": {
      "name": "Cloud Native Computing Foundation (CNCF)",
      "description": "CNCF is an open source software foundation that hosts and nurtures projects like Kubernetes and Prometheus.",
      "homepage": "https://www.cncf.io/",
      "city": "San Francisco",
      "region": "California",
      "country": "United States",
      "twitter": "https://twitter.com/cloudnativefdn",
      "linkedin": "https://www.linkedin.com/company/cloud-native-computing-foundation",
      "numEmployeesMin": 11,
      "numEmployeesMax": 50
    },
    "path": "Provisioning / Key Management",
    "landscape": "Provisioning / Key Management",
    "category": "Provisioning",
    "oss": true,
    "href": "/logos/spire.svg",
    "id": "spire"
  },
  {
    "name": "Rook",
    "homepage_url": "https://rook.io/",
    "repo_url": "https://github.com/rook/rook",
    "logo": "https://raw.githubusercontent.com/cncf/artwork/master/rook/stacked/color/rook-stacked-color.svg",
    "twitter": "https://twitter.com/rook_io",
    "crunchbase": "https://www.crunchbase.com/organization/cloud-native-computing-foundation",
    "github_data": {
      "stars": 2605,
      "license": "Apache-2.0",
      "description": "File, Block, and Object Storage Services for your Cloud-Native Environment",
      "latest_commit_date": "2018-04-07T00:00:00.000Z",
      "latest_commit_link": "/rook/rook/commit/e388eae6aa257622f18ac95a158522c18b91182a",
      "contributors_count": 63,
      "contributors_link": "https://github.com/rook/rook/graphs/contributors"
    },
    "github_start_commit_data": {
      "start_commit_link": "/rook/rook/commit/31bd4e46f5e7f1fcc38c4dc6ffe81e7a8d666458",
      "start_date": "2016-07-08T22:44:29Z"
    },
    "cncf_membership_data": {
      "cncf_member": "cncf"
    },
    "image_data": {
      "fileName": "rook.svg"
    },
    "cncfProject": "sandbox",
    "cncfMember": "cncf",
    "cncfRelation": "sandbox",
    "firstCommitDate": "2016-07-08T22:44:29Z",
    "firstCommitLink": "https://github.com/rook/rook/commit/31bd4e46f5e7f1fcc38c4dc6ffe81e7a8d666458",
    "latestCommitDate": {
      "text": "this week",
      "value": "990",
      "original": "2018-04-07T00:00:00.000Z"
    },
    "latestCommitLink": "https://github.com/rook/rook/commit/e388eae6aa257622f18ac95a158522c18b91182a",
    "contributorsCount": 63,
    "contributorsLink": "https://github.com/rook/rook/graphs/contributors",
    "stars": 2605,
    "license": "Apache-2.0",
    "headquarters": "San Francisco, California",
    "latestTweetDate": {
      "text": "this week",
      "value": "990",
      "original": "2018-04-06T03:00:07.000Z"
    },
    "description": "File, Block, and Object Storage Services for your Cloud-Native Environment",
    "organization": "Cloud Native Computing Foundation (CNCF)",
    "crunchbaseData": {
      "name": "Cloud Native Computing Foundation (CNCF)",
      "description": "CNCF is an open source software foundation that hosts and nurtures projects like Kubernetes and Prometheus.",
      "homepage": "https://www.cncf.io/",
      "city": "San Francisco",
      "region": "California",
      "country": "United States",
      "twitter": "https://twitter.com/cloudnativefdn",
      "linkedin": "https://www.linkedin.com/company/cloud-native-computing-foundation",
      "numEmployeesMin": 11,
      "numEmployeesMax": 50
    },
    "path": "Runtime / Cloud-Native Storage",
    "landscape": "Runtime / Cloud-Native Storage",
    "category": "Runtime",
    "oss": true,
    "href": "/logos/rook.svg",
    "id": "rook"
  },
  {
    "name": "containerd",
    "homepage_url": "https://containerd.io/",
    "repo_url": "https://github.com/containerd/containerd",
    "logo": "https://raw.githubusercontent.com/cncf/artwork/master/containerd/stacked/color/containerd-stacked-color.svg",
    "twitter": "https://twitter.com/containerd",
    "crunchbase": "https://www.crunchbase.com/organization/cloud-native-computing-foundation",
    "github_data": {
      "stars": 2436,
      "license": "Apache-2.0",
      "description": "An open and reliable container runtime",
      "latest_commit_date": "2018-04-06T00:00:00.000Z",
      "latest_commit_link": "/containerd/containerd/commit/076cf7f16ec1c4d60a23aeb3152b398181fafdde",
      "contributors_count": 121,
      "contributors_link": "https://github.com/containerd/containerd/graphs/contributors"
    },
    "github_start_commit_data": {
      "start_commit_link": "/containerd/containerd/commit/15a96783ca2ac8c0eb2c400701e8eb335059c63b",
      "start_date": "2015-11-05T23:29:53Z"
    },
    "cncf_membership_data": {
      "cncf_member": "cncf"
    },
    "image_data": {
      "fileName": "containerd.svg"
    },
    "cncfProject": "incubating",
    "cncfMember": "cncf",
    "cncfRelation": "incubating",
    "firstCommitDate": "2015-11-05T23:29:53Z",
    "firstCommitLink": "https://github.com/containerd/containerd/commit/15a96783ca2ac8c0eb2c400701e8eb335059c63b",
    "latestCommitDate": {
      "text": "this week",
      "value": "990",
      "original": "2018-04-06T00:00:00.000Z"
    },
    "latestCommitLink": "https://github.com/containerd/containerd/commit/076cf7f16ec1c4d60a23aeb3152b398181fafdde",
    "contributorsCount": 121,
    "contributorsLink": "https://github.com/containerd/containerd/graphs/contributors",
    "stars": 2436,
    "license": "Apache-2.0",
    "headquarters": "San Francisco, California",
    "latestTweetDate": {
      "text": "this week",
      "value": "990",
      "original": "2018-04-05T00:55:42.000Z"
    },
    "description": "An open and reliable container runtime",
    "organization": "Cloud Native Computing Foundation (CNCF)",
    "crunchbaseData": {
      "name": "Cloud Native Computing Foundation (CNCF)",
      "description": "CNCF is an open source software foundation that hosts and nurtures projects like Kubernetes and Prometheus.",
      "homepage": "https://www.cncf.io/",
      "city": "San Francisco",
      "region": "California",
      "country": "United States",
      "twitter": "https://twitter.com/cloudnativefdn",
      "linkedin": "https://www.linkedin.com/company/cloud-native-computing-foundation",
      "numEmployeesMin": 11,
      "numEmployeesMax": 50
    },
    "path": "Runtime / Container Runtime",
    "landscape": "Runtime / Container Runtime",
    "category": "Runtime",
    "oss": true,
    "href": "/logos/containerd.svg",
    "id": "containerd"
  },
  {
    "name": "rkt",
    "homepage_url": "https://github.com/rkt/rkt",
    "repo_url": "https://github.com/rkt/rkt",
    "logo": "https://raw.githubusercontent.com/cncf/artwork/master/rkt/stacked/color/rkt-stacked-color.svg",
    "crunchbase": "https://www.crunchbase.com/organization/cloud-native-computing-foundation",
    "github_data": {
      "stars": 7880,
      "license": "Apache-2.0",
      "description": "rkt is a pod-native container engine for Linux. It is composable, secure, and built on standards.",
      "latest_commit_date": "2018-04-06T00:00:00.000Z",
      "latest_commit_link": "/rkt/rkt/commit/6a38cb0cd1697005073d2221fd7cafb028910e01",
      "contributors_count": 198,
      "contributors_link": "https://github.com/rkt/rkt/graphs/contributors"
    },
    "github_start_commit_data": {
      "start_commit_link": "/rkt/rkt/commit/054de85da2173bb7857ed08032375fb643efeeac",
      "start_date": "2014-01-19T20:25:11Z"
    },
    "cncf_membership_data": {
      "cncf_member": "cncf"
    },
    "image_data": {
      "fileName": "rkt.svg"
    },
    "cncfProject": "incubating",
    "cncfMember": "cncf",
    "cncfRelation": "incubating",
    "firstCommitDate": "2014-01-19T20:25:11Z",
    "firstCommitLink": "https://github.com/rkt/rkt/commit/054de85da2173bb7857ed08032375fb643efeeac",
    "latestCommitDate": {
      "text": "this week",
      "value": "990",
      "original": "2018-04-06T00:00:00.000Z"
    },
    "latestCommitLink": "https://github.com/rkt/rkt/commit/6a38cb0cd1697005073d2221fd7cafb028910e01",
    "contributorsCount": 198,
    "contributorsLink": "https://github.com/rkt/rkt/graphs/contributors",
    "stars": 7880,
    "license": "Apache-2.0",
    "headquarters": "San Francisco, California",
    "twitter": "https://twitter.com/cloudnativefdn",
    "latestTweetDate": {
      "text": "this week",
      "value": "990",
      "original": "2018-04-08T12:57:01.000Z"
    },
    "description": "rkt is a pod-native container engine for Linux. It is composable, secure, and built on standards.",
    "organization": "Cloud Native Computing Foundation (CNCF)",
    "crunchbaseData": {
      "name": "Cloud Native Computing Foundation (CNCF)",
      "description": "CNCF is an open source software foundation that hosts and nurtures projects like Kubernetes and Prometheus.",
      "homepage": "https://www.cncf.io/",
      "city": "San Francisco",
      "region": "California",
      "country": "United States",
      "twitter": "https://twitter.com/cloudnativefdn",
      "linkedin": "https://www.linkedin.com/company/cloud-native-computing-foundation",
      "numEmployeesMin": 11,
      "numEmployeesMax": 50
    },
    "path": "Runtime / Container Runtime",
    "landscape": "Runtime / Container Runtime",
    "category": "Runtime",
    "oss": true,
    "href": "/logos/rkt.svg",
    "id": "rkt"
  },
  {
    "name": "CNI",
    "homepage_url": "https://github.com/containernetworking",
    "repo_url": "https://github.com/containernetworking/cni",
    "logo": "https://raw.githubusercontent.com/cncf/artwork/master/cni/stacked/color/cni-stacked-color.svg",
    "crunchbase": "https://www.crunchbase.com/organization/cloud-native-computing-foundation",
    "github_data": {
      "stars": 1246,
      "license": "Apache-2.0",
      "description": "Container Network Interface - networking for Linux containers",
      "latest_commit_date": "2018-03-07T00:00:00.000Z",
      "latest_commit_link": "/containernetworking/cni/commit/a700ea864b5f1852d179ce83e8bc169f0b4a0ef4",
      "release_date": "2017-04-05T17:46:24Z",
      "release_link": "https://github.com/containernetworking/cni/releases",
      "contributors_count": 70,
      "contributors_link": "https://github.com/containernetworking/cni/graphs/contributors"
    },
    "github_start_commit_data": {
      "start_commit_link": "/containernetworking/cni/commit/502be19aed3557ddb775fe133b095ad6e6eb87bf",
      "start_date": "2015-04-05T03:35:49Z"
    },
    "cncf_membership_data": {
      "cncf_member": "cncf"
    },
    "image_data": {
      "fileName": "cni.svg"
    },
    "cncfProject": "incubating",
    "cncfMember": "cncf",
    "cncfRelation": "incubating",
    "firstCommitDate": "2015-04-05T03:35:49Z",
    "firstCommitLink": "https://github.com/containernetworking/cni/commit/502be19aed3557ddb775fe133b095ad6e6eb87bf",
    "latestCommitDate": {
      "text": "about a month",
      "value": "960",
      "original": "2018-03-07T00:00:00.000Z"
    },
    "latestCommitLink": "https://github.com/containernetworking/cni/commit/a700ea864b5f1852d179ce83e8bc169f0b4a0ef4",
    "releaseDate": "2017-04-05T17:46:24Z",
    "releaseLink": "https://github.com/containernetworking/cni/releases",
    "contributorsCount": 70,
    "contributorsLink": "https://github.com/containernetworking/cni/graphs/contributors",
    "stars": 1246,
    "license": "Apache-2.0",
    "headquarters": "San Francisco, California",
    "twitter": "https://twitter.com/cloudnativefdn",
    "latestTweetDate": {
      "text": "this week",
      "value": "990",
      "original": "2018-04-08T12:57:01.000Z"
    },
    "description": "Container Network Interface - networking for Linux containers",
    "organization": "Cloud Native Computing Foundation (CNCF)",
    "crunchbaseData": {
      "name": "Cloud Native Computing Foundation (CNCF)",
      "description": "CNCF is an open source software foundation that hosts and nurtures projects like Kubernetes and Prometheus.",
      "homepage": "https://www.cncf.io/",
      "city": "San Francisco",
      "region": "California",
      "country": "United States",
      "twitter": "https://twitter.com/cloudnativefdn",
      "linkedin": "https://www.linkedin.com/company/cloud-native-computing-foundation",
      "numEmployeesMin": 11,
      "numEmployeesMax": 50
    },
    "path": "Runtime / Cloud-Native Network",
    "landscape": "Runtime / Cloud-Native Network",
    "category": "Runtime",
    "oss": true,
    "href": "/logos/cni.svg",
    "id": "cni"
  },
  {
    "name": "Kubernetes",
    "description": "Kubernetes is an open-source system for automating deployment, scaling, and management of containerized applications",
    "homepage_url": "https://kubernetes.io/",
    "repo_url": "https://github.com/kubernetes/kubernetes",
    "logo": "https://raw.githubusercontent.com/cncf/artwork/master/kubernetes/stacked/color/kubernetes-stacked-color.svg",
    "twitter": "https://twitter.com/kubernetesio",
    "crunchbase": "https://www.crunchbase.com/organization/cloud-native-computing-foundation",
    "github_data": {
      "stars": 34790,
      "license": "Apache-2.0",
      "description": "Production-Grade Container Scheduling and Management",
      "latest_commit_date": "2018-04-08T00:00:00.000Z",
      "latest_commit_link": "/kubernetes/kubernetes/commit/d39bfa0d138368bbe72b0eaf434501dcb4ec9908",
      "release_date": "2018-04-05T17:15:46Z",
      "release_link": "https://github.com/kubernetes/kubernetes/releases",
      "contributors_count": 1639,
      "contributors_link": "https://github.com/kubernetes/kubernetes/graphs/contributors"
    },
    "github_start_commit_data": {
      "start_commit_link": "/kubernetes/kubernetes/commit/2c4b3a562ce34cddc3f8218a2c4d11c7310e6d56",
      "start_date": "2014-06-06T23:40:48Z"
    },
    "cncf_membership_data": {
      "cncf_member": "cncf"
    },
    "image_data": {
      "fileName": "kubernetes.svg"
    },
    "cncfProject": "graduated",
    "cncfMember": "cncf",
    "cncfRelation": "graduated",
    "firstCommitDate": "2014-06-06T23:40:48Z",
    "firstCommitLink": "https://github.com/kubernetes/kubernetes/commit/2c4b3a562ce34cddc3f8218a2c4d11c7310e6d56",
    "latestCommitDate": {
      "text": "this week",
      "value": "990",
      "original": "2018-04-08T00:00:00.000Z"
    },
    "latestCommitLink": "https://github.com/kubernetes/kubernetes/commit/d39bfa0d138368bbe72b0eaf434501dcb4ec9908",
    "releaseDate": {
      "text": "this week",
      "value": "990",
      "original": "2018-04-05T17:15:46Z"
    },
    "releaseLink": "https://github.com/kubernetes/kubernetes/releases",
    "contributorsCount": 1639,
    "contributorsLink": "https://github.com/kubernetes/kubernetes/graphs/contributors",
    "stars": 34790,
    "license": "Apache-2.0",
    "headquarters": "San Francisco, California",
    "latestTweetDate": {
      "text": "this week",
      "value": "990",
      "original": "2018-04-06T16:20:35.000Z"
    },
    "organization": "Cloud Native Computing Foundation (CNCF)",
    "crunchbaseData": {
      "name": "Cloud Native Computing Foundation (CNCF)",
      "description": "CNCF is an open source software foundation that hosts and nurtures projects like Kubernetes and Prometheus.",
      "homepage": "https://www.cncf.io/",
      "city": "San Francisco",
      "region": "California",
      "country": "United States",
      "twitter": "https://twitter.com/cloudnativefdn",
      "linkedin": "https://www.linkedin.com/company/cloud-native-computing-foundation",
      "numEmployeesMin": 11,
      "numEmployeesMax": 50
    },
    "path": "Orchestration & Management / Scheduling & Orchestration",
    "landscape": "Orchestration & Management / Scheduling & Orchestration",
    "category": "Orchestration & Management",
    "oss": true,
    "href": "/logos/kubernetes.svg",
    "id": "kubernetes"
  },
  {
    "name": "CoreDNS",
    "homepage_url": "https://coredns.io/",
    "repo_url": "https://github.com/coredns/coredns",
    "logo": "https://github.com/cncf/artwork/blob/master/coredns/stacked/color/coredns-stacked-color.svg",
    "twitter": "https://twitter.com/corednsio",
    "crunchbase": "https://www.crunchbase.com/organization/cloud-native-computing-foundation",
    "github_data": {
      "stars": 1819,
      "license": "Apache-2.0",
      "description": "CoreDNS is a DNS server that chains plugins",
      "latest_commit_date": "2018-04-06T00:00:00.000Z",
      "latest_commit_link": "/coredns/coredns/commit/5a546f743e2d694524db8d5ce02415f53d6cd045",
      "contributors_count": 75,
      "contributors_link": "https://github.com/coredns/coredns/graphs/contributors"
    },
    "github_start_commit_data": {
      "start_commit_link": "/coredns/coredns/commit/3ec0d9fe6b133a64712ae69fd712c14ad1a71f4d",
      "start_date": "2016-03-18T20:57:35Z"
    },
    "cncf_membership_data": {
      "cncf_member": "cncf"
    },
    "image_data": {
      "fileName": "core-dns.svg"
    },
    "cncfProject": "incubating",
    "cncfMember": "cncf",
    "cncfRelation": "incubating",
    "firstCommitDate": "2016-03-18T20:57:35Z",
    "firstCommitLink": "https://github.com/coredns/coredns/commit/3ec0d9fe6b133a64712ae69fd712c14ad1a71f4d",
    "latestCommitDate": {
      "text": "this week",
      "value": "990",
      "original": "2018-04-06T00:00:00.000Z"
    },
    "latestCommitLink": "https://github.com/coredns/coredns/commit/5a546f743e2d694524db8d5ce02415f53d6cd045",
    "contributorsCount": 75,
    "contributorsLink": "https://github.com/coredns/coredns/graphs/contributors",
    "stars": 1819,
    "license": "Apache-2.0",
    "headquarters": "San Francisco, California",
    "latestTweetDate": {
      "text": "last week",
      "value": "980",
      "original": "2018-04-01T15:23:05.000Z"
    },
    "description": "CoreDNS is a DNS server that chains plugins",
    "organization": "Cloud Native Computing Foundation (CNCF)",
    "crunchbaseData": {
      "name": "Cloud Native Computing Foundation (CNCF)",
      "description": "CNCF is an open source software foundation that hosts and nurtures projects like Kubernetes and Prometheus.",
      "homepage": "https://www.cncf.io/",
      "city": "San Francisco",
      "region": "California",
      "country": "United States",
      "twitter": "https://twitter.com/cloudnativefdn",
      "linkedin": "https://www.linkedin.com/company/cloud-native-computing-foundation",
      "numEmployeesMin": 11,
      "numEmployeesMax": 50
    },
    "path": "Orchestration & Management / Coordination & Service Discovery",
    "landscape": "Orchestration & Management / Coordination & Service Discovery",
    "category": "Orchestration & Management",
    "oss": true,
    "href": "/logos/core-dns.svg",
    "id": "core-dns"
  },
  {
    "name": "Envoy",
    "homepage_url": "https://envoyproxy.github.io/",
    "repo_url": "https://github.com/envoyproxy/envoy",
    "logo": "https://github.com/cncf/artwork/blob/master/envoy/stacked/color/envoy-stacked-color.svg",
    "twitter": "https://twitter.com/envoyproxy",
    "crunchbase": "https://www.crunchbase.com/organization/cloud-native-computing-foundation",
    "github_data": {
      "stars": 4450,
      "license": "Apache-2.0",
      "description": "C++ front/service proxy",
      "latest_commit_date": "2018-04-06T00:00:00.000Z",
      "latest_commit_link": "/envoyproxy/envoy/commit/34b87b6451c913601efc4ffcdeaf4dd2e53d37eb",
      "contributors_count": 148,
      "contributors_link": "https://github.com/envoyproxy/envoy/graphs/contributors"
    },
    "github_start_commit_data": {
      "start_commit_link": "/envoyproxy/envoy/commit/a714b9c2b0a2acc9da44098cabff69586134a0dd",
      "start_date": "2016-08-08T15:07:25Z"
    },
    "cncf_membership_data": {
      "cncf_member": "cncf"
    },
    "image_data": {
      "fileName": "envoy.svg"
    },
    "cncfProject": "incubating",
    "cncfMember": "cncf",
    "cncfRelation": "incubating",
    "firstCommitDate": "2016-08-08T15:07:25Z",
    "firstCommitLink": "https://github.com/envoyproxy/envoy/commit/a714b9c2b0a2acc9da44098cabff69586134a0dd",
    "latestCommitDate": {
      "text": "this week",
      "value": "990",
      "original": "2018-04-06T00:00:00.000Z"
    },
    "latestCommitLink": "https://github.com/envoyproxy/envoy/commit/34b87b6451c913601efc4ffcdeaf4dd2e53d37eb",
    "contributorsCount": 148,
    "contributorsLink": "https://github.com/envoyproxy/envoy/graphs/contributors",
    "stars": 4450,
    "license": "Apache-2.0",
    "headquarters": "San Francisco, California",
    "latestTweetDate": {
      "text": "this week",
      "value": "990",
      "original": "2018-04-05T16:09:02.000Z"
    },
    "description": "C++ front/service proxy",
    "organization": "Cloud Native Computing Foundation (CNCF)",
    "crunchbaseData": {
      "name": "Cloud Native Computing Foundation (CNCF)",
      "description": "CNCF is an open source software foundation that hosts and nurtures projects like Kubernetes and Prometheus.",
      "homepage": "https://www.cncf.io/",
      "city": "San Francisco",
      "region": "California",
      "country": "United States",
      "twitter": "https://twitter.com/cloudnativefdn",
      "linkedin": "https://www.linkedin.com/company/cloud-native-computing-foundation",
      "numEmployeesMin": 11,
      "numEmployeesMax": 50
    },
    "path": "Orchestration & Management / Service Management",
    "landscape": "Orchestration & Management / Service Management",
    "category": "Orchestration & Management",
    "oss": true,
    "href": "/logos/envoy.svg",
    "id": "envoy"
  },
  {
    "name": "gRPC",
    "homepage_url": "https://grpc.io/",
    "repo_url": "https://github.com/grpc/grpc",
    "logo": "https://raw.githubusercontent.com/cncf/artwork/master/grpc/horizontal/color/grpc-horizontal-color.svg",
    "twitter": "https://twitter.com/grpcio",
    "crunchbase": "https://www.crunchbase.com/organization/cloud-native-computing-foundation",
    "github_data": {
      "stars": 14647,
      "license": "Apache-2.0",
      "description": "The C based gRPC (C++, Python, Ruby, Objective-C, PHP, C#)",
      "latest_commit_date": "2018-04-08T00:00:00.000Z",
      "latest_commit_link": "/grpc/grpc/commit/9a79b78e3b49510912668827fe580c4871441083",
      "contributors_count": 335,
      "contributors_link": "https://github.com/grpc/grpc/graphs/contributors"
    },
    "github_start_commit_data": {
      "start_commit_link": "/grpc/grpc/commit/0e905e63db21bcdd85d3d1af051fcdc5bb5caa38",
      "start_date": "2014-11-22T00:16:16Z"
    },
    "cncf_membership_data": {
      "cncf_member": "cncf"
    },
    "image_data": {
      "fileName": "g-rpc.svg"
    },
    "cncfProject": "incubating",
    "cncfMember": "cncf",
    "cncfRelation": "incubating",
    "firstCommitDate": "2014-11-22T00:16:16Z",
    "firstCommitLink": "https://github.com/grpc/grpc/commit/0e905e63db21bcdd85d3d1af051fcdc5bb5caa38",
    "latestCommitDate": {
      "text": "this week",
      "value": "990",
      "original": "2018-04-08T00:00:00.000Z"
    },
    "latestCommitLink": "https://github.com/grpc/grpc/commit/9a79b78e3b49510912668827fe580c4871441083",
    "contributorsCount": 335,
    "contributorsLink": "https://github.com/grpc/grpc/graphs/contributors",
    "stars": 14647,
    "license": "Apache-2.0",
    "headquarters": "San Francisco, California",
    "latestTweetDate": {
      "text": "last week",
      "value": "980",
      "original": "2018-03-28T19:32:06.000Z"
    },
    "description": "The C based gRPC (C++, Python, Ruby, Objective-C, PHP, C#)",
    "organization": "Cloud Native Computing Foundation (CNCF)",
    "crunchbaseData": {
      "name": "Cloud Native Computing Foundation (CNCF)",
      "description": "CNCF is an open source software foundation that hosts and nurtures projects like Kubernetes and Prometheus.",
      "homepage": "https://www.cncf.io/",
      "city": "San Francisco",
      "region": "California",
      "country": "United States",
      "twitter": "https://twitter.com/cloudnativefdn",
      "linkedin": "https://www.linkedin.com/company/cloud-native-computing-foundation",
      "numEmployeesMin": 11,
      "numEmployeesMax": 50
    },
    "path": "Orchestration & Management / Service Management",
    "landscape": "Orchestration & Management / Service Management",
    "category": "Orchestration & Management",
    "oss": true,
    "href": "/logos/g-rpc.svg",
    "id": "g-rpc"
  },
  {
    "name": "Linkerd",
    "homepage_url": "https://linkerd.io/",
    "repo_url": "https://github.com/linkerd/linkerd",
    "logo": "https://raw.githubusercontent.com/cncf/artwork/master/linkerd/stacked/color/linkerd-stacked-color.svg",
    "twitter": "https://twitter.com/linkerd",
    "crunchbase": "https://www.crunchbase.com/organization/cloud-native-computing-foundation",
    "github_data": {
      "stars": 3843,
      "license": "Apache-2.0",
      "description": "Production-grade feature-rich service mesh for any platform",
      "latest_commit_date": "2018-04-05T00:00:00.000Z",
      "latest_commit_link": "/linkerd/linkerd/commit/7cc7b8dc69287f442c8f22fed04fb1910246b896",
      "contributors_count": 68,
      "contributors_link": "https://github.com/linkerd/linkerd/graphs/contributors"
    },
    "github_start_commit_data": {
      "start_commit_link": "/linkerd/linkerd/commit/37e38f2a892d9354eea7305135aa6370612b02f2",
      "start_date": "2016-01-13T22:17:47Z"
    },
    "cncf_membership_data": {
      "cncf_member": "cncf"
    },
    "image_data": {
      "fileName": "linkerd.svg"
    },
    "cncfProject": "incubating",
    "cncfMember": "cncf",
    "cncfRelation": "incubating",
    "firstCommitDate": "2016-01-13T22:17:47Z",
    "firstCommitLink": "https://github.com/linkerd/linkerd/commit/37e38f2a892d9354eea7305135aa6370612b02f2",
    "latestCommitDate": {
      "text": "this week",
      "value": "990",
      "original": "2018-04-05T00:00:00.000Z"
    },
    "latestCommitLink": "https://github.com/linkerd/linkerd/commit/7cc7b8dc69287f442c8f22fed04fb1910246b896",
    "contributorsCount": 68,
    "contributorsLink": "https://github.com/linkerd/linkerd/graphs/contributors",
    "stars": 3843,
    "license": "Apache-2.0",
    "headquarters": "San Francisco, California",
    "latestTweetDate": {
      "text": "this week",
      "value": "990",
      "original": "2018-04-04T19:55:02.000Z"
    },
    "description": "Production-grade feature-rich service mesh for any platform",
    "organization": "Cloud Native Computing Foundation (CNCF)",
    "crunchbaseData": {
      "name": "Cloud Native Computing Foundation (CNCF)",
      "description": "CNCF is an open source software foundation that hosts and nurtures projects like Kubernetes and Prometheus.",
      "homepage": "https://www.cncf.io/",
      "city": "San Francisco",
      "region": "California",
      "country": "United States",
      "twitter": "https://twitter.com/cloudnativefdn",
      "linkedin": "https://www.linkedin.com/company/cloud-native-computing-foundation",
      "numEmployeesMin": 11,
      "numEmployeesMax": 50
    },
    "path": "Orchestration & Management / Service Management",
    "landscape": "Orchestration & Management / Service Management",
    "category": "Orchestration & Management",
    "oss": true,
    "href": "/logos/linkerd.svg",
    "id": "linkerd"
  },
  {
    "name": "Open Policy Agent (OPA)",
    "homepage_url": "https://www.openpolicyagent.org/",
    "repo_url": "https://github.com/open-policy-agent/opa",
    "logo": "./hosted_logos/opa.svg",
    "twitter": "https://twitter.com/openpolicyagent",
    "crunchbase": "https://www.crunchbase.com/organization/cloud-native-computing-foundation",
    "github_data": {
      "stars": 295,
      "license": "Apache-2.0",
      "description": "An open source project to policy-enable your service.",
      "latest_commit_date": "2018-04-08T00:00:00.000Z",
      "latest_commit_link": "/open-policy-agent/opa/commit/75c7fefa0e19054d733c0583b84a866fc1be5095",
      "contributors_count": 18,
      "contributors_link": "https://github.com/open-policy-agent/opa/graphs/contributors"
    },
    "github_start_commit_data": {
      "start_commit_link": "/open-policy-agent/opa/commit/7eb56674c51d286afa134861ba282bf7a13668c6",
      "start_date": "2015-12-28T22:08:25Z"
    },
    "cncf_membership_data": {
      "cncf_member": "cncf"
    },
    "image_data": {
      "fileName": "open-policy-agent-opa.svg",
      "hash": "1tC4W5h6uvHUbgyUMfw6qLf6VLngchvlURGNNNLuDzM="
    },
    "cncfProject": "sandbox",
    "cncfMember": "cncf",
    "cncfRelation": "sandbox",
    "firstCommitDate": "2015-12-28T22:08:25Z",
    "firstCommitLink": "https://github.com/open-policy-agent/opa/commit/7eb56674c51d286afa134861ba282bf7a13668c6",
    "latestCommitDate": {
      "text": "this week",
      "value": "990",
      "original": "2018-04-08T00:00:00.000Z"
    },
    "latestCommitLink": "https://github.com/open-policy-agent/opa/commit/75c7fefa0e19054d733c0583b84a866fc1be5095",
    "contributorsCount": 18,
    "contributorsLink": "https://github.com/open-policy-agent/opa/graphs/contributors",
    "stars": 295,
    "license": "Apache-2.0",
    "headquarters": "San Francisco, California",
    "latestTweetDate": {
      "text": "this week",
      "value": "990",
      "original": "2018-04-04T21:44:15.000Z"
    },
    "description": "An open source project to policy-enable your service.",
    "organization": "Cloud Native Computing Foundation (CNCF)",
    "crunchbaseData": {
      "name": "Cloud Native Computing Foundation (CNCF)",
      "description": "CNCF is an open source software foundation that hosts and nurtures projects like Kubernetes and Prometheus.",
      "homepage": "https://www.cncf.io/",
      "city": "San Francisco",
      "region": "California",
      "country": "United States",
      "twitter": "https://twitter.com/cloudnativefdn",
      "linkedin": "https://www.linkedin.com/company/cloud-native-computing-foundation",
      "numEmployeesMin": 11,
      "numEmployeesMax": 50
    },
    "path": "Orchestration & Management / Service Management",
    "landscape": "Orchestration & Management / Service Management",
    "category": "Orchestration & Management",
    "oss": true,
    "href": "/logos/open-policy-agent-opa.svg",
    "id": "open-policy-agent-opa"
  },
  {
    "name": "Vitess",
    "homepage_url": "https://vitess.io/",
    "logo": "https://raw.githubusercontent.com/cncf/artwork/master/vitess/stacked/color/vitess-stacked-color.svg",
    "repo_url": "https://github.com/youtube/vitess",
    "twitter": "https://twitter.com/vitessio",
    "crunchbase": "https://www.crunchbase.com/organization/cloud-native-computing-foundation",
    "github_data": {
      "stars": 5800,
      "license": "Apache-2.0",
      "description": "Vitess is a database clustering system for horizontal scaling of MySQL.",
      "latest_commit_date": "2018-04-08T00:00:00.000Z",
      "latest_commit_link": "/vitessio/vitess/commit/901b767c8a43df1e6f88cf8ffde081588f7e9ccc",
      "release_date": "2017-02-02T18:05:51Z",
      "release_link": "https://github.com/youtube/vitess/releases",
      "contributors_count": 113,
      "contributors_link": "https://github.com/youtube/vitess/graphs/contributors"
    },
    "github_start_commit_data": {
      "start_commit_link": "/youtube/vitess/commit/8d483dc19ef660938bae3564af95d48a8017275f",
      "start_date": "2012-02-25T07:19:43Z"
    },
    "cncf_membership_data": {
      "cncf_member": "cncf"
    },
    "image_data": {
      "fileName": "vitess.svg"
    },
    "cncfProject": "incubating",
    "cncfMember": "cncf",
    "cncfRelation": "incubating",
    "firstCommitDate": "2012-02-25T07:19:43Z",
    "firstCommitLink": "https://github.com/youtube/vitess/commit/8d483dc19ef660938bae3564af95d48a8017275f",
    "latestCommitDate": {
      "text": "this week",
      "value": "990",
      "original": "2018-04-08T00:00:00.000Z"
    },
    "latestCommitLink": "https://github.com/vitessio/vitess/commit/901b767c8a43df1e6f88cf8ffde081588f7e9ccc",
    "releaseDate": "2017-02-02T18:05:51Z",
    "releaseLink": "https://github.com/youtube/vitess/releases",
    "contributorsCount": 113,
    "contributorsLink": "https://github.com/youtube/vitess/graphs/contributors",
    "stars": 5800,
    "license": "Apache-2.0",
    "headquarters": "San Francisco, California",
    "latestTweetDate": {
      "text": "last week",
      "value": "980",
      "original": "2018-03-28T13:00:46.000Z"
    },
    "description": "Vitess is a database clustering system for horizontal scaling of MySQL.",
    "organization": "Cloud Native Computing Foundation (CNCF)",
    "crunchbaseData": {
      "name": "Cloud Native Computing Foundation (CNCF)",
      "description": "CNCF is an open source software foundation that hosts and nurtures projects like Kubernetes and Prometheus.",
      "homepage": "https://www.cncf.io/",
      "city": "San Francisco",
      "region": "California",
      "country": "United States",
      "twitter": "https://twitter.com/cloudnativefdn",
      "linkedin": "https://www.linkedin.com/company/cloud-native-computing-foundation",
      "numEmployeesMin": 11,
      "numEmployeesMax": 50
    },
    "path": "App Definition and Development / Database and Data Warehouse",
    "landscape": "App Definition and Development / Database and Data Warehouse",
    "category": "App Definition and Development",
    "oss": true,
    "href": "/logos/vitess.svg",
    "id": "vitess"
  },
  {
    "name": "NATS",
    "homepage_url": "https://nats.io/",
    "repo_url": "https://github.com/nats-io/gnatsd",
    "logo": "https://raw.githubusercontent.com/cncf/artwork/master/nats/stacked/color/nats-stacked-color.svg",
    "twitter": "https://twitter.com/nats_io",
    "crunchbase": "https://www.crunchbase.com/organization/cloud-native-computing-foundation",
    "github_data": {
      "stars": 3963,
      "license": "Apache-2.0",
      "description": "High-Performance server for NATS, the cloud native messaging system.",
      "latest_commit_date": "2018-03-29T00:00:00.000Z",
      "latest_commit_link": "/nats-io/gnatsd/commit/e8b524aed6da4091892045fa80bd1b2ee2df5529",
      "contributors_count": 47,
      "contributors_link": "https://github.com/nats-io/gnatsd/graphs/contributors"
    },
    "github_start_commit_data": {
      "start_commit_link": "/nats-io/gnatsd/commit/6c33e7b1607eee12533e7e9aa952cdf70a7bc24b",
      "start_date": "2012-10-29T16:12:25Z"
    },
    "cncf_membership_data": {
      "cncf_member": "cncf"
    },
    "image_data": {
      "fileName": "nats.svg"
    },
    "cncfProject": "incubating",
    "cncfMember": "cncf",
    "cncfRelation": "incubating",
    "firstCommitDate": "2012-10-29T16:12:25Z",
    "firstCommitLink": "https://github.com/nats-io/gnatsd/commit/6c33e7b1607eee12533e7e9aa952cdf70a7bc24b",
    "latestCommitDate": {
      "text": "last week",
      "value": "980",
      "original": "2018-03-29T00:00:00.000Z"
    },
    "latestCommitLink": "https://github.com/nats-io/gnatsd/commit/e8b524aed6da4091892045fa80bd1b2ee2df5529",
    "contributorsCount": 47,
    "contributorsLink": "https://github.com/nats-io/gnatsd/graphs/contributors",
    "stars": 3963,
    "license": "Apache-2.0",
    "headquarters": "San Francisco, California",
    "latestTweetDate": {
      "text": "this week",
      "value": "990",
      "original": "2018-04-06T21:43:46.000Z"
    },
    "description": "High-Performance server for NATS, the cloud native messaging system.",
    "organization": "Cloud Native Computing Foundation (CNCF)",
    "crunchbaseData": {
      "name": "Cloud Native Computing Foundation (CNCF)",
      "description": "CNCF is an open source software foundation that hosts and nurtures projects like Kubernetes and Prometheus.",
      "homepage": "https://www.cncf.io/",
      "city": "San Francisco",
      "region": "California",
      "country": "United States",
      "twitter": "https://twitter.com/cloudnativefdn",
      "linkedin": "https://www.linkedin.com/company/cloud-native-computing-foundation",
      "numEmployeesMin": 11,
      "numEmployeesMax": 50
    },
    "path": "App Definition and Development / Streaming",
    "landscape": "App Definition and Development / Streaming",
    "category": "App Definition and Development",
    "oss": true,
    "href": "/logos/nats.svg",
    "id": "nats"
  },
  {
    "name": "Prometheus",
    "homepage_url": "https://prometheus.io/",
    "repo_url": "https://github.com/prometheus/prometheus",
    "logo": "https://raw.githubusercontent.com/cncf/artwork/master/prometheus/stacked/color/prometheus-stacked-color.svg",
    "twitter": "https://twitter.com/PrometheusIO",
    "crunchbase": "https://www.crunchbase.com/organization/cloud-native-computing-foundation",
    "github_data": {
      "stars": 15695,
      "license": "Apache-2.0",
      "description": "The Prometheus monitoring system and time series database.",
      "latest_commit_date": "2018-04-08T00:00:00.000Z",
      "latest_commit_link": "/prometheus/prometheus/commit/464e747f1e0853809be6122786b7f13db6aa93e7",
      "contributors_count": 237,
      "contributors_link": "https://github.com/prometheus/prometheus/graphs/contributors"
    },
    "github_start_commit_data": {
      "start_commit_link": "/prometheus/prometheus/commit/734d28b515026ca9f429eba0a7d09954bceb6387",
      "start_date": "2012-11-24T11:14:12Z"
    },
    "cncf_membership_data": {
      "cncf_member": "cncf"
    },
    "image_data": {
      "fileName": "prometheus.svg"
    },
    "cncfProject": "incubating",
    "cncfMember": "cncf",
    "cncfRelation": "incubating",
    "firstCommitDate": "2012-11-24T11:14:12Z",
    "firstCommitLink": "https://github.com/prometheus/prometheus/commit/734d28b515026ca9f429eba0a7d09954bceb6387",
    "latestCommitDate": {
      "text": "this week",
      "value": "990",
      "original": "2018-04-08T00:00:00.000Z"
    },
    "latestCommitLink": "https://github.com/prometheus/prometheus/commit/464e747f1e0853809be6122786b7f13db6aa93e7",
    "contributorsCount": 237,
    "contributorsLink": "https://github.com/prometheus/prometheus/graphs/contributors",
    "stars": 15695,
    "license": "Apache-2.0",
    "headquarters": "San Francisco, California",
    "latestTweetDate": {
      "text": "this week",
      "value": "990",
      "original": "2018-04-02T08:25:51.000Z"
    },
    "description": "The Prometheus monitoring system and time series database.",
    "organization": "Cloud Native Computing Foundation (CNCF)",
    "crunchbaseData": {
      "name": "Cloud Native Computing Foundation (CNCF)",
      "description": "CNCF is an open source software foundation that hosts and nurtures projects like Kubernetes and Prometheus.",
      "homepage": "https://www.cncf.io/",
      "city": "San Francisco",
      "region": "California",
      "country": "United States",
      "twitter": "https://twitter.com/cloudnativefdn",
      "linkedin": "https://www.linkedin.com/company/cloud-native-computing-foundation",
      "numEmployeesMin": 11,
      "numEmployeesMax": 50
    },
    "path": "Observability and Analysis / Monitoring",
    "landscape": "Observability and Analysis / Monitoring",
    "category": "Observability and Analysis",
    "oss": true,
    "href": "/logos/prometheus.svg",
    "id": "prometheus"
  },
  {
    "name": "Fluentd",
    "homepage_url": "https://www.fluentd.org/",
    "repo_url": "https://github.com/fluent/fluentd",
    "logo": "https://raw.githubusercontent.com/cncf/artwork/master/fluentd/stacked/color/fluentd-stacked-color.svg",
    "twitter": "https://twitter.com/fluentd",
    "crunchbase": "https://www.crunchbase.com/organization/cloud-native-computing-foundation",
    "github_data": {
      "stars": 6211,
      "license": "Apache-2.0",
      "description": "Fluentd: Unified Logging Layer (project under CNCF)",
      "latest_commit_date": "2018-04-05T00:00:00.000Z",
      "latest_commit_link": "/fluent/fluentd/commit/0fa6a2de0498c0f48fe3bf577804f560f3dfdf0c",
      "release_date": "2018-04-04T11:22:20Z",
      "release_link": "https://github.com/fluent/fluentd/releases",
      "contributors_count": 134,
      "contributors_link": "https://github.com/fluent/fluentd/graphs/contributors"
    },
    "github_start_commit_data": {
      "start_commit_link": "/fluent/fluentd/commit/5c14d05ff44d08d180f5d6de8bbedf3f84a23d25",
      "start_date": "2011-06-18T22:36:35Z"
    },
    "cncf_membership_data": {
      "cncf_member": "cncf"
    },
    "image_data": {
      "fileName": "fluentd.svg"
    },
    "cncfProject": "incubating",
    "cncfMember": "cncf",
    "cncfRelation": "incubating",
    "firstCommitDate": "2011-06-18T22:36:35Z",
    "firstCommitLink": "https://github.com/fluent/fluentd/commit/5c14d05ff44d08d180f5d6de8bbedf3f84a23d25",
    "latestCommitDate": {
      "text": "this week",
      "value": "990",
      "original": "2018-04-05T00:00:00.000Z"
    },
    "latestCommitLink": "https://github.com/fluent/fluentd/commit/0fa6a2de0498c0f48fe3bf577804f560f3dfdf0c",
    "releaseDate": {
      "text": "this week",
      "value": "990",
      "original": "2018-04-04T11:22:20Z"
    },
    "releaseLink": "https://github.com/fluent/fluentd/releases",
    "contributorsCount": 134,
    "contributorsLink": "https://github.com/fluent/fluentd/graphs/contributors",
    "stars": 6211,
    "license": "Apache-2.0",
    "headquarters": "San Francisco, California",
    "latestTweetDate": {
      "text": "this week",
      "value": "990",
      "original": "2018-04-08T18:01:12.000Z"
    },
    "description": "Fluentd: Unified Logging Layer (project under CNCF)",
    "organization": "Cloud Native Computing Foundation (CNCF)",
    "crunchbaseData": {
      "name": "Cloud Native Computing Foundation (CNCF)",
      "description": "CNCF is an open source software foundation that hosts and nurtures projects like Kubernetes and Prometheus.",
      "homepage": "https://www.cncf.io/",
      "city": "San Francisco",
      "region": "California",
      "country": "United States",
      "twitter": "https://twitter.com/cloudnativefdn",
      "linkedin": "https://www.linkedin.com/company/cloud-native-computing-foundation",
      "numEmployeesMin": 11,
      "numEmployeesMax": 50
    },
    "path": "Observability and Analysis / Logging",
    "landscape": "Observability and Analysis / Logging",
    "category": "Observability and Analysis",
    "oss": true,
    "href": "/logos/fluentd.svg",
    "id": "fluentd"
  },
  {
    "name": "Jaeger",
    "homepage_url": "http://jaegertracing.io/",
    "repo_url": "https://github.com/jaegertracing/jaeger",
    "logo": "https://raw.githubusercontent.com/cncf/artwork/master/jaeger/stacked/color/jaeger-stacked-color.svg",
    "twitter": "https://twitter.com/JaegerTracing",
    "crunchbase": "https://www.crunchbase.com/organization/cloud-native-computing-foundation",
    "github_data": {
      "stars": 4374,
      "license": "Apache-2.0",
      "description": "CNCF Jaeger, a Distributed Tracing System",
      "latest_commit_date": "2018-04-07T00:00:00.000Z",
      "latest_commit_link": "/jaegertracing/jaeger/commit/1ae65e0cbda15e44199aee24bdd62393a1f9dbd4",
      "contributors_count": 42,
      "contributors_link": "https://github.com/jaegertracing/jaeger/graphs/contributors"
    },
    "github_start_commit_data": {
      "start_commit_link": "/jaegertracing/jaeger/commit/4dc35c9e83518c339cbf0bc52c7b39cd028e7659",
      "start_date": "2016-04-18T22:22:11Z"
    },
    "cncf_membership_data": {
      "cncf_member": "cncf"
    },
    "image_data": {
      "fileName": "jaeger.svg"
    },
    "cncfProject": "incubating",
    "cncfMember": "cncf",
    "cncfRelation": "incubating",
    "firstCommitDate": "2016-04-18T22:22:11Z",
    "firstCommitLink": "https://github.com/jaegertracing/jaeger/commit/4dc35c9e83518c339cbf0bc52c7b39cd028e7659",
    "latestCommitDate": {
      "text": "this week",
      "value": "990",
      "original": "2018-04-07T00:00:00.000Z"
    },
    "latestCommitLink": "https://github.com/jaegertracing/jaeger/commit/1ae65e0cbda15e44199aee24bdd62393a1f9dbd4",
    "contributorsCount": 42,
    "contributorsLink": "https://github.com/jaegertracing/jaeger/graphs/contributors",
    "stars": 4374,
    "license": "Apache-2.0",
    "headquarters": "San Francisco, California",
    "latestTweetDate": {
      "text": "this week",
      "value": "990",
      "original": "2018-04-05T15:01:14.000Z"
    },
    "description": "CNCF Jaeger, a Distributed Tracing System",
    "organization": "Cloud Native Computing Foundation (CNCF)",
    "crunchbaseData": {
      "name": "Cloud Native Computing Foundation (CNCF)",
      "description": "CNCF is an open source software foundation that hosts and nurtures projects like Kubernetes and Prometheus.",
      "homepage": "https://www.cncf.io/",
      "city": "San Francisco",
      "region": "California",
      "country": "United States",
      "twitter": "https://twitter.com/cloudnativefdn",
      "linkedin": "https://www.linkedin.com/company/cloud-native-computing-foundation",
      "numEmployeesMin": 11,
      "numEmployeesMax": 50
    },
    "path": "Observability and Analysis / Tracing",
    "landscape": "Observability and Analysis / Tracing",
    "category": "Observability and Analysis",
    "oss": true,
    "href": "/logos/jaeger.svg",
    "id": "jaeger"
  },
  {
    "name": "OpenTracing",
    "homepage_url": "http://opentracing.io/",
    "repo_url": "https://github.com/opentracing/opentracing-go",
    "logo": "https://raw.githubusercontent.com/cncf/artwork/master/opentracing/stacked/color/opentracing-stacked-color.svg",
    "twitter": "https://twitter.com/opentracing",
    "crunchbase": "https://www.crunchbase.com/organization/cloud-native-computing-foundation",
    "github_data": {
      "stars": 1045,
      "license": "Apache-2.0",
      "description": "OpenTracing API for Go",
      "latest_commit_date": "2018-04-06T00:00:00.000Z",
      "latest_commit_link": "/opentracing/opentracing-go/commit/5a4c9c6b841c283274c4b55324f9da7257d8c211",
      "release_date": "2017-02-06T22:16:52Z",
      "release_link": "https://github.com/opentracing/opentracing-go/releases",
      "contributors_count": 31,
      "contributors_link": "https://github.com/opentracing/opentracing-go/graphs/contributors"
    },
    "github_start_commit_data": {
      "start_commit_link": "/opentracing/opentracing-go/commit/3089998b243182f7b28fbbad3229e0fad871ecbf",
      "start_date": "2015-11-26T06:23:17Z"
    },
    "cncf_membership_data": {
      "cncf_member": "cncf"
    },
    "image_data": {
      "fileName": "open-tracing.svg"
    },
    "cncfProject": "incubating",
    "cncfMember": "cncf",
    "cncfRelation": "incubating",
    "firstCommitDate": "2015-11-26T06:23:17Z",
    "firstCommitLink": "https://github.com/opentracing/opentracing-go/commit/3089998b243182f7b28fbbad3229e0fad871ecbf",
    "latestCommitDate": {
      "text": "this week",
      "value": "990",
      "original": "2018-04-06T00:00:00.000Z"
    },
    "latestCommitLink": "https://github.com/opentracing/opentracing-go/commit/5a4c9c6b841c283274c4b55324f9da7257d8c211",
    "releaseDate": "2017-02-06T22:16:52Z",
    "releaseLink": "https://github.com/opentracing/opentracing-go/releases",
    "contributorsCount": 31,
    "contributorsLink": "https://github.com/opentracing/opentracing-go/graphs/contributors",
    "stars": 1045,
    "license": "Apache-2.0",
    "headquarters": "San Francisco, California",
    "latestTweetDate": {
      "text": "this week",
      "value": "990",
      "original": "2018-04-06T15:55:23.000Z"
    },
    "description": "OpenTracing API for Go",
    "organization": "Cloud Native Computing Foundation (CNCF)",
    "crunchbaseData": {
      "name": "Cloud Native Computing Foundation (CNCF)",
      "description": "CNCF is an open source software foundation that hosts and nurtures projects like Kubernetes and Prometheus.",
      "homepage": "https://www.cncf.io/",
      "city": "San Francisco",
      "region": "California",
      "country": "United States",
      "twitter": "https://twitter.com/cloudnativefdn",
      "linkedin": "https://www.linkedin.com/company/cloud-native-computing-foundation",
      "numEmployeesMin": 11,
      "numEmployeesMax": 50
    },
    "path": "Observability and Analysis / Tracing",
    "landscape": "Observability and Analysis / Tracing",
    "category": "Observability and Analysis",
    "oss": true,
    "href": "/logos/open-tracing.svg",
    "id": "open-tracing"
  }
]